chatbot_kernel/__init__.py
chatbot_kernel/__main__.py
chatbot_kernel/kernel.py
chatbot_kernel/kernelspec.py
chatbot_kernel-0.4.1.dist-info/METADATA
chatbot_kernel-0.4.1.dist-info/WHEEL
chatbot_kernel-0.4.1.dist-info/licenses/LICENSE
chatbot_kernel-0.4.1.dist-info/RECORD
