Metadata-Version: 2.4
Name: chatbot-kernel
Version: 0.4.1
Summary: A Jupyter kernel using LLM models from Huggingface
Project-URL: Homepage, https://github.com/appolloford/chatbot_kernel
Author-email: "Chia-Jung Hsu @ C3SE" <chiajung.hsu@chalmers.se>
License-File: LICENSE
Classifier: Intended Audience :: Developers
Classifier: License :: OSI Approved :: BSD License
Classifier: Programming Language :: Python :: 3
Requires-Python: >=3.8
Requires-Dist: ipykernel
Requires-Dist: jupyter-client
Requires-Dist: vllm
Provides-Extra: dev
Requires-Dist: black; extra == 'dev'
Requires-Dist: pre-commit; extra == 'dev'
Provides-Extra: test
Requires-Dist: jupyter-kernel-test; extra == 'test'
